pysessionmanager/__init__.py
pysessionmanager/codes.py
pysessionmanager/core.py
pysessionmanager/presistence.py
pysessionmanager/security.py
pysessionmanager/test_test.py
pysessionmanager/utils.py
pysessionmanager-1.6.4.dist-info/LICENSE
pysessionmanager-1.6.4.dist-info/METADATA
pysessionmanager-1.6.4.dist-info/WHEEL
pysessionmanager-1.6.4.dist-info/top_level.txt
pysessionmanager-1.6.4.dist-info/RECORD
