Metadata-Version: 2.2
Name: pysessionmanager
Version: 1.6.4
Summary: 1.6.4 - A Python library for managing user sessions with password protection, expiration, and persistent storage. Ideal for web applications and CLI tools. Supports session locking, unlocking, and time-based expiration. Compatible with Flask and Django. Includes a command-line interface for easy session management. Features include session creation, deletion, listing, and restoration. Provides secure session handling with hashing and encryption. 
Author: Ahmad Al Dibo
Author-email: ahmadaldibo212009@gmail.com
License: MIT
Keywords: session management,Python session manager,password protection,session expiration,TTL,persistent storage,CLI,web applications,Flask,Django,user authentication,security,session timeout,Python library,session handling,hashing,user sessions,authentication management,session protection,time-based expiration,persistent sessions,Python CLI tools,session control,session lifecycle,Python web apps,PyPI
Classifier: Programming Language :: Python :: 3
Classifier: License :: OSI Approved :: MIT License
Classifier: Operating System :: OS Independent
Requires-Python: >=3.6
License-File: LICENSE
Dynamic: author
Dynamic: author-email
Dynamic: classifier
Dynamic: description
Dynamic: description-content-type
Dynamic: keywords
Dynamic: license
Dynamic: requires-python
Dynamic: summary
